aruana/__init__.py
aruana/aruana.py
aruana/genders.py
aruana/same_words.py
aruana/stopwords.py
aruana/strings.py
aruana/vocab.py
Aruana-1.1.1.dist-info/LICENSE
Aruana-1.1.1.dist-info/METADATA
Aruana-1.1.1.dist-info/WHEEL
Aruana-1.1.1.dist-info/top_level.txt
Aruana-1.1.1.dist-info/RECORD
