Metadata-Version: 2.1
Name: Aruana
Version: 1.1.1
Summary: Aruana is a collection of methods that can be used for simple NLP tasks and for machine learning text preprocessing.
Home-page: https://aruana.nheeng.com
Author: Nheeng
Author-email: contact@nheeng.com
License: Apache
Platform: UNKNOWN
